keycloak/__init__.py
keycloak/authz.py
keycloak/client.py
keycloak/exceptions.py
keycloak/mixins.py
keycloak/openid_connect.py
keycloak/realm.py
keycloak/uma.py
keycloak/uma1.py
keycloak/well_known.py
keycloak/admin/__init__.py
keycloak/admin/clients.py
keycloak/admin/realm.py
keycloak/admin/roles.py
keycloak/admin/users.py
keycloak/aio/__init__.py
keycloak/aio/abc.py
keycloak/aio/authz.py
keycloak/aio/client.py
keycloak/aio/mixins.py
keycloak/aio/openid_connect.py
keycloak/aio/realm.py
keycloak/aio/uma.py
keycloak/aio/well_known.py
python_keycloak_client-0.2.2.dist-info/LICENSE
python_keycloak_client-0.2.2.dist-info/METADATA
python_keycloak_client-0.2.2.dist-info/WHEEL
python_keycloak_client-0.2.2.dist-info/top_level.txt
python_keycloak_client-0.2.2.dist-info/RECORD
