Metadata-Version: 2.1
Name: python-keycloak-client
Version: 0.2.2
Summary: Install Python Keycloak client.
Home-page: https://github.com/Peter-Slump/python-keycloak-client
Author: Peter Slump
Author-email: peter@yarf.nl
License: MIT
Platform: UNKNOWN
Requires-Dist: requests
Requires-Dist: python-jose
Provides-Extra: aio
Requires-Dist: aiohttp (<4,>=3.4.4) ; (python_full_version >= "3.5.3") and extra == 'aio'
Provides-Extra: dev
Requires-Dist: bumpversion (==0.5.3) ; extra == 'dev'
Requires-Dist: twine ; extra == 'dev'
Provides-Extra: doc
Requires-Dist: Sphinx (==1.4.4) ; extra == 'doc'
Requires-Dist: sphinx-autobuild (==0.6.0) ; extra == 'doc'
